async_tiff-0.3.0.dist-info/METADATA
async_tiff-0.3.0.dist-info/WHEEL
async_tiff/__init__.py
async_tiff/_async_tiff.abi3.so
async_tiff/_async_tiff.pyi
async_tiff/_decoder.pyi
async_tiff/_geo.pyi
async_tiff/_ifd.pyi
async_tiff/_thread_pool.pyi
async_tiff/_tiff.pyi
async_tiff/_tile.pyi
async_tiff/enums.py
async_tiff/py.typed
async_tiff-0.3.0.dist-info/RECORD
