Metadata-Version: 2.4
Name: async-tiff
Version: 0.3.0
Classifier: Programming Language :: Rust
Classifier: Programming Language :: Python :: Implementation :: CPython
Classifier: Programming Language :: Python :: Implementation :: PyPy
Requires-Dist: obspec>=0.1.0b3
Requires-Python: >=3.10
